PointInPolygon/__init__.py
test/PointInPolygonTest.py
test/__init__.py
PointInPolygon-1.0.2.dist-info/LICENSE
PointInPolygon-1.0.2.dist-info/METADATA
PointInPolygon-1.0.2.dist-info/WHEEL
PointInPolygon-1.0.2.dist-info/top_level.txt
PointInPolygon-1.0.2.dist-info/RECORD
