Metadata-Version: 2.1
Name: PointInPolygon
Version: 1.0.2
Summary: This python package is used to check point inside/outside of polygon/multipolygon. It is supported polygon to array, convert multipolygon dataframe to polygon, find the min and max item in 2D array.
Home-page: https://github.com/Iceloof/PointInPolygon
Author: Hurin Hu
Author-email: hurin@live.ca
License: UNKNOWN
Platform: UNKNOWN
Classifier: Programming Language :: Python
Classifier: Programming Language :: Python :: 3.6
Classifier: Programming Language :: Python :: 3.7
Classifier: Programming Language :: Python :: 3.8
Classifier: License :: OSI Approved :: MIT License
Classifier: Operating System :: OS Independent
